Cu3t0mAPI/CU3T0MAPI.py
Cu3t0mAPI/__init__.py
Cu3t0mAPI-1.8.7.dist-info/LICENCE
Cu3t0mAPI-1.8.7.dist-info/METADATA
Cu3t0mAPI-1.8.7.dist-info/WHEEL
Cu3t0mAPI-1.8.7.dist-info/top_level.txt
Cu3t0mAPI-1.8.7.dist-info/RECORD
