Metadata-Version: 2.1
Name: Cu3t0mAPI
Version: 1.8.7
Summary: A Python API Wrapper
Home-page: https://github.com/Custom/Cu3t0mAPI
Author: Diwan Mohamed Faheer
Author-email: diwanmohamedfaheer@gmail.com
License: UNKNOWN
Platform: UNKNOWN
Classifier: Programming Language :: Python :: 3
Classifier: License :: OSI Approved :: MIT License
Classifier: Operating System :: OS Independent
Requires-Python: >=3.6
